jupyterscad/__init__.py
jupyterscad/_render.py
jupyterscad/_view.py
jupyterscad/exceptions.py
jupyterscad-1.0.dist-info/COPYING
jupyterscad-1.0.dist-info/LICENSE
jupyterscad-1.0.dist-info/METADATA
jupyterscad-1.0.dist-info/WHEEL
jupyterscad-1.0.dist-info/top_level.txt
jupyterscad-1.0.dist-info/RECORD
