Metadata-Version: 2.1
Name: jupyterscad
Version: 1.0
Summary: Solid 3D Cad (SCAD) renderer and viewer for Jupyter
Author: Jennifer Reiber Kyle
License: GPLv3
Project-URL: Homepage, https://jreiberkyle.github.io/jupyterscad/
Project-URL: Documentation, https://jreiberkyle.github.io/jupyterscad/
Project-URL: Repository, https://github.com/jreiberkyle/jupyterscad
Project-URL: Changelog, https://github.com/jreiberkyle/jupyterscad/blob/main/CHANGELOG.md
Keywords: openscad,scad,jupyter,jupyterlab,notebook,viewer,render,solidpython,solidpython2
Classifier: Development Status :: 6 - Mature
Classifier: Programming Language :: Python :: 3
Requires-Python: >=3.8
License-File: LICENSE
License-File: COPYING
Requires-Dist: numpy-stl
Requires-Dist: ipywidgets
Requires-Dist: pythreejs
Provides-Extra: docs
Requires-Dist: mkdocs <2 ; extra == 'docs'
Requires-Dist: mkdocs-material <10 ; extra == 'docs'
Requires-Dist: mkdocstrings-python ; extra == 'docs'
Provides-Extra: test
Requires-Dist: pytest ; extra == 'test'
Requires-Dist: solidpython2 ; extra == 'test'
